apb_slave.v
module apb_slave (
      	//input signal 
	input pclk ,
	input rst , 
	input psel ,
	input penable,
	input pwrite ,
	input [7:0] paddr,
	input [15:0] pwdata,
	//output signal
	output reg [15:0] prdata,
	output pready
);
	parameter IDLE = 3'b001;
	parameter SETUP = 3'b010;
	parameter ACCESS = 3'b100;

	reg [2:0] cst, nxt;
	assign pready = 1;

	logic [15:0] mem [0:255] ;
	reg acc_ena;

	always @(posedge pclk or posedge rst) begin
		if ( rst) 
			cst <= IDLE;
		else 
			cst <= nxt ;
	end

	always @(posedge pclk) begin 
		if (acc_ena) begin 
			if (pwrite)
					mem[paddr] <= pwdata;
				else 
					prdata 	   <= mem[paddr];
			end
		end

	always @* begin 
		acc_ena =0 ;
		case (cst) 
			IDLE: 
				if (psel) 
					nxt = SETUP;
				else 
					nxt = cst;
			SETUP:
				if(penable) 
				begin
					nxt = ACCESS;
				end

				else    nxt = cst;


			ACCESS: begin
					acc_ena = 1;
				
					if (psel) 
						nxt = SETUP;
					else
						nxt = IDLE;
				end
			default: ;	
			endcase
		end

endmodule

tb.v
module apb_slave_tb;

  // Testbench signals
  reg pclk;
  reg rst;
  reg psel;
  reg penable;
  reg pwrite;
  reg [7:0] paddr;
  reg [15:0] pwdata;
  wire [15:0] prdata;
  wire pready;

  // Instantiate the apb_slave module
  apb_slave uut (
    .pclk(pclk),
    .rst(rst),
    .psel(psel),
    .penable(penable),
    .pwrite(pwrite),
    .paddr(paddr),
    .pwdata(pwdata),
    .prdata(prdata),
    .pready(pready)
  );

  // Clock generation
  always begin
    #5 pclk = ~pclk;  // 100MHz clock
  end

  // Test sequence
  initial begin
    // Initialize signals
    pclk = 0;
    rst = 0;
    psel = 0;
    penable = 0;
    pwrite = 0;
    paddr = 8'b0;
    pwdata = 16'b0;

    // Set up waveform dump
    $dumpfile("apb_slave_tb.vcd");   // VCD file to store the waveform
    $dumpvars(0, apb_slave_tb);       // Dump all signals from the testbench module

    // Apply reset
    rst = 1;
    #10 rst = 0; // Release reset

    // Test Case 1: Write to memory
    psel = 1; pwrite = 1; paddr = 8'h10; pwdata = 16'hA5A5;
    #10 penable = 1;  // Start write operation
    #10 penable = 0;  // End write operation
    psel = 0;

    // Test Case 2: Read from memory
    psel = 1; pwrite = 0; paddr = 8'h10; pwdata = 16'b0;
    #10 penable = 1;  // Start read operation
    #10 penable = 0;  // End read operation
    psel = 0;

    // Test Case 3: Idle state
    #20 psel = 0; penable = 0; pwrite = 0;

    // End simulation
    #50 $finish;
  end

  // Monitor the outputs
  initial begin
    $monitor("Time: %0t | pclk: %b | rst: %b | psel: %b | penable: %b | pwrite: %b | paddr: %h | pwdata: %h | prdata: %h | pready: %b", 
             $time, pclk, rst, psel, penable, pwrite, paddr, pwdata, prdata, pready);
  end

endmodule

apb_slave_tb.vcd
$date
	Thu Apr 17 08:59:11 2025
$end
$version
	Icarus Verilog
$end
$timescale
	1s
$end
$scope module apb_slave_tb $end
$var wire 1 ! pready $end
$var wire 16 " prdata [15:0] $end
$var reg 8 # paddr [7:0] $end
$var reg 1 $ pclk $end
$var reg 1 % penable $end
$var reg 1 & psel $end
$var reg 16 ' pwdata [15:0] $end
$var reg 1 ( pwrite $end
$var reg 1 ) rst $end
$scope module uut $end
$var wire 8 * paddr [7:0] $end
$var wire 1 $ pclk $end
$var wire 1 % penable $end
$var wire 1 ! pready $end
$var wire 1 & psel $end
$var wire 16 + pwdata [15:0] $end
$var wire 1 ( pwrite $end
$var wire 1 ) rst $end
$var reg 1 , acc_ena $end
$var reg 3 - cst [2:0] $end
$var reg 3 . nxt [2:0] $end
$var reg 16 / prdata [15:0] $end
$upscope $end
$upscope $end
$enddefinitions $end
#0
$dumpvars
bx /
b1 .
b1 -
0,
b0 +
b0 *
1)
0(
b0 '
0&
0%
0$
b0 #
bx "
1!
$end
#5
1$
#10
b10 .
0$
b1010010110100101 '
b1010010110100101 +
b10000 #
b10000 *
1(
1&
0)
#15
b10 -
1$
#20
b100 .
0$
1%
#25
b10 .
1,
b100 -
1$
#30
1,
0$
b0 '
b0 +
0(
1&
0%
#35
0,
b10 -
1$
#40
b100 .
0$
1%
#45
b10 .
1,
b100 -
1$
#50
b1 .
1,
0$
0&
0%
#55
0,
b1 -
1$
