apbslave.v
module apbslave(
	input pclk ,
	input rst,
	input psel,
	input penable,
	input [7:0] paddr,
	input [15:0] pwdata,
	input pwrite,
	output pready ,
	output reg [15:0] prdata

);
	parameter IDLE = 3'b001;
	parameter SETUP= 3'b010;
	parameter ACCESS= 3'b100;
	reg [2:0] cur_st,nx_st;
	reg dev_sel;
	logic [15:0] mem [0:255];

	assign pready = 1'b1;
	always @(*) begin
		dev_sel=0;
		case (cur_st) 
			IDLE :   
				if(psel) 
					nx_st=SETUP;
				
				else 
					nx_st    =cur_st;
				
			SETUP:
				if(penable)
					nx_st = ACCESS;
				else 	
					nx_st = cur_st;

			ACCESS: begin 
				dev_sel = 1;

				if(psel) 
					nx_st= SETUP;
				else    
					nx_st = IDLE;
				end
			default: ;
		endcase
	end
	
	always @(posedge pclk or posedge rst) begin
			if(rst) 
				cur_st <= IDLE ;
			else 	
			
			begin
				cur_st <= nx_st;

				if(dev_sel)
				
				begin
					if (pwrite)
				
					mem[paddr] <= pwdata;
				
					else 
					prdata <= mem[paddr];
				
				end
		 	end
	end

endmodule

apbslave_tb.v
`timescale 1ns/10ps
`define PERIOD 10  

module apbslave_tb;
 	reg pclk ;
	reg rst;
	reg psel;
	reg penable;
	reg [7:0] paddr;
	reg [15:0] pwdata;
	reg pwrite;	
	wire pready;
	wire [15:0] prdata;
	
	apbslave DUT (pclk ,rst, psel , penable, paddr , pwdata, pwrite, pready,prdata );
	
	integer i,j;
	initial begin
	pclk =0 ;
	forever #((`PERIOD)/2) pclk = ~pclk ; 
	end

	task write_data ();
	
	begin		
	i=0;
	//write transaction
        repeat(256)
	begin

	psel =1 ;
        //#(`PERIOD ); //setup state
        
	waitforclk(1);
	penable =1 ;
        pwrite =1 ;
        paddr = i;
        pwdata = i;
        //#(`PERIOD ); //access
	waitforclk(1);
        while (!pready )
        	#(`PERIOD ); //wait 1 clk
	$display("wdata: %d ",DUT.mem[i]);
	i = i +1;
	end
	end

	endtask
	
	task read_data();
        begin
	j=0;
	repeat (256)
	begin	
	psel =1 ;
	#(`PERIOD ); //setup state 
	penable =1 ;
	pwrite =0 ;
	paddr = j;
	//pwdata = 16'haa55;
	#(`PERIOD ); //access
	while (!pready ) 
	  	#(`PERIOD ); //wait 1 clk 
	$display("rdata: %d ",DUT.mem[j]);
	j = j+1;
	end
	end
	endtask

	task waitforclk (input integer n) ; 
		repeat(n) 
			@(posedge pclk) ;	
	endtask
	
	initial begin
	$dumpfile("apbslave.vcd");
	$dumpvars(0,apbslave_tb);
	
	rst = 1;
	psel =0 ;
	penable =0 ;
	paddr = 0 ;
	pwdata =0;
	pwrite =0 ;
	#0.1
	#(`PERIOD *2);


	rst =0 ;
	psel =1;
/*
	waitforclk(1);
	write_data();
	psel=1;
	waitforclk(1);
	read_data();
	waitforclk(5);
*/
		//write_data();
	psel =1 ;
        #(`PERIOD ); //setup state
        penable=1 ;
        pwrite = 1 ;
        paddr  = 8'b00000000;
        pwdata = 16'haa55;
        #(`PERIOD); //access
        while (!pready )
                #(`PERIOD ); //wait 1 clk
	waitforclk(1);

	psel =1 ;
        #(`PERIOD ); //setup state
        penable = 1 ;
        pwrite  = 0 ;
        paddr   = 8'b00000000;
        //pwdata = 16'haa55;
        #(`PERIOD ); //access
        while (!pready )
                #(`PERIOD ); //wait 1 clk
	//read_data();
	waitforclk(10);
	
	/*
	//write transaction 
	psel =1 ;
	#(`PERIOD ); //setup state 
	penable =1 ;
	pwrite =1 ;
	paddr = 8'b00001011;
	pwdata = 16'haa55;
	#(`PERIOD ); //access
	while (!pready ) 
	  	#(`PERIOD ); //wait 1 clk 

	*/	
	//psel =0 ;
	//penable =0 ; 
	//pwrite  =0 ;
		
/*	
	//read transaction 
	//#(`PERIOD*3);
	psel =1 ;
	#(`PERIOD ); //setup state 
	penable =1 ;
	pwrite =0 ;
	//paddr = 8'b00001011;
	//pwdata = 16'haa55;
	#(`PERIOD ); //access
	while (!pready ) 
	  	#(`PERIOD ); //wait 1 clk 

	//write transaction 
	psel =1 ;
	#(`PERIOD ); //setup state 
	penable =1 ;
	pwrite =1 ;
	paddr = 8'b00001100;
	pwdata = 16'haa56;
	#(`PERIOD ); //access
	while (!pready ) 
	  	#(`PERIOD ); //wait 1 clk 
	
	//read transaction 
	psel =1 ;
	#(`PERIOD ); //setup state 
	penable =1 ;
	pwrite =0 ;
	paddr = 8'b00001100;
	//pwdata = 16'haa55;
	#(`PERIOD ); //access
	while (!pready ) 
	  	#(`PERIOD ); //wait 1 clk 
	
		
		#(`PERIOD);//wait for one clk
	*/
	$finish ();

	end

	endmodule

apbslave.vcd
$date
	Fri Apr 18 16:59:17 2025
$end
$version
	Icarus Verilog
$end
$timescale
	10ps
$end
$scope module apbslave_tb $end
$var wire 1 ! pready $end
$var wire 16 " prdata [15:0] $end
$var reg 8 # paddr [7:0] $end
$var reg 1 $ pclk $end
$var reg 1 % penable $end
$var reg 1 & psel $end
$var reg 16 ' pwdata [15:0] $end
$var reg 1 ( pwrite $end
$var reg 1 ) rst $end
$var integer 32 * i [31:0] $end
$var integer 32 + j [31:0] $end
$scope module DUT $end
$var wire 8 , paddr [7:0] $end
$var wire 1 $ pclk $end
$var wire 1 % penable $end
$var wire 1 ! pready $end
$var wire 1 & psel $end
$var wire 16 - pwdata [15:0] $end
$var wire 1 ( pwrite $end
$var wire 1 ) rst $end
$var reg 3 . cur_st [2:0] $end
$var reg 1 / dev_sel $end
$var reg 3 0 nx_st [2:0] $end
$var reg 16 1 prdata [15:0] $end
$upscope $end
$scope task read_data $end
$upscope $end
$scope task waitforclk $end
$var integer 32 2 n [31:0] $end
$upscope $end
$scope task write_data $end
$upscope $end
$upscope $end
$enddefinitions $end
#0
$dumpvars
bx 2
bx 1
b1 0
0/
b1 .
b0 -
b0 ,
bx +
bx *
1)
0(
b0 '
0&
0%
0$
b0 #
bx "
1!
$end
#500
1$
#1000
0$
#1500
1$
#2000
0$
#2010
b10 0
1&
0)
#2500
b10 .
1$
#3000
0$
#3010
b100 0
b1010101001010101 '
b1010101001010101 -
1(
1%
#3500
b10 0
1/
b100 .
1$
#4000
0$
#4010
b1 2
#4500
b100 0
0/
b10 .
1$
#5000
0$
#5500
b10 0
1/
b100 .
1$
0(
#6000
0$
#6500
b100 0
0/
b1010101001010101 "
b1010101001010101 1
b10 .
1$
b1010 2
#7000
0$
#7500
b10 0
1/
b100 .
1$
#8000
0$
#8500
b100 0
0/
b10 .
1$
#9000
0$
#9500
b10 0
1/
b100 .
1$
#10000
0$
#10500
b100 0
0/
b10 .
1$
#11000
0$
#11500
b10 0
1/
b100 .
1$
#12000
0$
#12500
b100 0
0/
b10 .
1$
#13000
0$
#13500
b10 0
1/
b100 .
1$
#14000
0$
#14500
b100 0
0/
b10 .
1$
#15000
0$
#15500
b10 0
1/
b100 .
1$
