apbslave.v
module apbslave(
	input pclk ,
	input rst,
	input psel,
	input penable,
	input [7:0] paddr,
	input [15:0] pwdata,
	input pwrite,
	output pready ,
	output reg [15:0] prdata

);
	parameter IDLE = 3'b001;
	parameter SETUP= 3'b010;
	parameter ACCESS= 3'b100;
	reg [2:0] cur_st,nx_st;
	reg dev_sel;
	logic [15:0] mem [0:255];

	assign pready = 1'b1;
	always @(*) begin
		dev_sel=0;
		case (cur_st) 
			IDLE :   
				if(psel) 
					nx_st=SETUP;
				
				else 
					nx_st    =cur_st;
				
			SETUP:
				if(penable)
					nx_st = ACCESS;
				else 	
					nx_st = cur_st;

			ACCESS: begin 
				dev_sel = 1;

				if(psel) 
					nx_st= SETUP;
				else    
					nx_st = IDLE;
				end
			default: ;
		endcase
	end
	
	always @(posedge pclk or posedge rst) begin
			if(rst) 
				cur_st <= IDLE ;
			else 	
			
			begin
				cur_st <= nx_st;

				if(dev_sel)
				
				begin
					if (pwrite)
				
					mem[paddr] <= pwdata;
				
					else 
					prdata <= mem[paddr];
				
				end
		 	end
	end

endmodule

apbslave_tb.v
`timescale 1ns/10ps
`define PERIOD 10  

module apbslave_tb;
 	reg pclk ;
	reg rst;
	reg psel;
	reg penable;
	reg [7:0] paddr;
	reg [15:0] pwdata;
	reg pwrite;	
	wire pready;
	wire [15:0] prdata;
	
	apbslave DUT (pclk ,rst, psel , penable, paddr , pwdata, pwrite, pready,prdata );
	
	integer i,j;
	initial begin
	pclk =0 ;
	forever #((`PERIOD)/2) pclk = ~pclk ; 
	end

	task write_data ();
	
	begin		
	i=0;
	//write transaction
        repeat(256)
	begin

	psel =1 ;
        //#(`PERIOD ); //setup state
        
	waitforclk(1);
	penable =1 ;
        pwrite =1 ;
        paddr = i;
        pwdata = i;
        //#(`PERIOD ); //access
	waitforclk(1);
        while (!pready )
        	#(`PERIOD ); //wait 1 clk
	$display("wdata: %d ",DUT.mem[i]);
	i = i +1;
	end
	end

	endtask
	
	task read_data();
        begin
	j=0;
	repeat (256)
	begin	
	psel =1 ;
	#(`PERIOD ); //setup state 
	penable =1 ;
	pwrite =0 ;
	paddr = j;
	//pwdata = 16'haa55;
	#(`PERIOD ); //access
	while (!pready ) 
	  	#(`PERIOD ); //wait 1 clk 
	$display("rdata: %d ",DUT.mem[j]);
	j = j+1;
	end
	end
	endtask

	task waitforclk (input integer n) ; 
		repeat(n) 
			@(posedge pclk) ;	
	endtask
	
	initial begin
	$dumpfile("apbslave.vcd");
	$dumpvars(0,apbslave_tb);
	
	rst = 1;
	psel =0 ;
	penable =0 ;
	paddr = 0 ;
	pwdata =0;
	pwrite =0 ;
	#0.1;
	#(`PERIOD *2);


	rst =0;
	psel =1;
	paddr=0;
	penable=1;
	pwrite = 1;
	waitforclk(1);
	write_data();
	waitforclk(1);
	read_data();
	waitforclk(5);
/*
		//write_data();
	psel =1 ;
        #(`PERIOD ); //setup state
        penable=1 ;
        pwrite = 1 ;
        paddr  = 8'b00000000;
        pwdata = 16'haa55;
        #(`PERIOD); //access
        while (!pready )
                #(`PERIOD ); //wait 1 clk
	waitforclk(1);

	psel =1 ;
        #(`PERIOD ); //setup state
        penable = 1 ;
        pwrite  = 0 ;
        paddr   = 8'b00000000;
        //pwdata = 16'haa55;
        #(`PERIOD ); //access
        while (!pready )
                #(`PERIOD ); //wait 1 clk
	//read_data();
	waitforclk(10);
	
	
	//write transaction 
	psel =1 ;
	#(`PERIOD ); //setup state 
	penable =1 ;
	pwrite =1 ;
	paddr = 8'b00001011;
	pwdata = 16'haa55;
	#(`PERIOD ); //access
	while (!pready ) 
	  	#(`PERIOD ); //wait 1 clk 

*/	
	//psel =0 ;
	//penable =0 ; 
	//pwrite  =0 ;
		
/*	
	//read transaction 
	//#(`PERIOD*3);
	psel =1 ;
	#(`PERIOD ); //setup state 
	penable =1 ;
	pwrite =0 ;
	//paddr = 8'b00001011;
	//pwdata = 16'haa55;
	#(`PERIOD ); //access
	while (!pready ) 
	  	#(`PERIOD ); //wait 1 clk 

	//write transaction 
	psel =1 ;
	#(`PERIOD ); //setup state 
	penable =1 ;
	pwrite =1 ;
	paddr = 8'b00001100;
	pwdata = 16'haa56;
	#(`PERIOD ); //access
	while (!pready ) 
	  	#(`PERIOD ); //wait 1 clk 
	
	//read transaction 
	psel =1 ;
	#(`PERIOD ); //setup state 
	penable =1 ;
	pwrite =0 ;
	paddr = 8'b00001100;
	//pwdata = 16'haa55;
	#(`PERIOD ); //access
	while (!pready ) 
	  	#(`PERIOD ); //wait 1 clk 
	
		
		#(`PERIOD);//wait for one clk
*/
	$finish ();

	end

	endmodule

apbslave.vcd
$date
	Mon Apr 21 09:43:41 2025
$end
$version
	Icarus Verilog
$end
$timescale
	10ps
$end
$scope module apbslave_tb $end
$var wire 1 ! pready $end
$var wire 16 " prdata [15:0] $end
$var reg 8 # paddr [7:0] $end
$var reg 1 $ pclk $end
$var reg 1 % penable $end
$var reg 1 & psel $end
$var reg 16 ' pwdata [15:0] $end
$var reg 1 ( pwrite $end
$var reg 1 ) rst $end
$var integer 32 * i [31:0] $end
$var integer 32 + j [31:0] $end
$scope module DUT $end
$var wire 8 , paddr [7:0] $end
$var wire 1 $ pclk $end
$var wire 1 % penable $end
$var wire 1 ! pready $end
$var wire 1 & psel $end
$var wire 16 - pwdata [15:0] $end
$var wire 1 ( pwrite $end
$var wire 1 ) rst $end
$var reg 3 . cur_st [2:0] $end
$var reg 1 / dev_sel $end
$var reg 3 0 nx_st [2:0] $end
$var reg 16 1 prdata [15:0] $end
$upscope $end
$scope task read_data $end
$upscope $end
$scope task waitforclk $end
$var integer 32 2 n [31:0] $end
$upscope $end
$scope task write_data $end
$upscope $end
$upscope $end
$enddefinitions $end
#0
$dumpvars
bx 2
bx 1
b1 0
0/
b1 .
b0 -
b0 ,
bx +
bx *
1)
0(
b0 '
0&
0%
0$
b0 #
bx "
1!
$end
#500
1$
#1000
0$
#1500
1$
#2000
0$
#2010
b10 0
b1 2
1(
1%
1&
0)
#2500
b100 0
b10 .
b0 *
1$
#3000
0$
#3500
b10 0
1/
b100 .
1$
#4000
0$
#4500
b100 0
0/
b10 .
b1 *
1$
#5000
0$
#5500
b10 0
1/
b100 .
b1 '
b1 -
b1 #
b1 ,
1$
#6000
0$
#6500
b100 0
0/
b10 .
b10 *
1$
#7000
0$
#7500
b10 0
1/
b100 .
b10 '
b10 -
b10 #
b10 ,
1$
#8000
0$
#8500
b100 0
0/
b10 .
b11 *
1$
#9000
0$
#9500
b10 0
1/
b100 .
b11 '
b11 -
b11 #
b11 ,
1$
#10000
0$
#10500
b100 0
0/
b10 .
b100 *
1$
#11000
0$
#11500
b10 0
1/
b100 .
b100 '
b100 -
b100 #
b100 ,
1$
#12000
0$
#12500
b100 0
0/
b10 .
b101 *
1$
#13000
0$
#13500
b10 0
1/
b100 .
b101 '
b101 -
b101 #
b101 ,
1$
#14000
0$
#14500
b100 0
0/
b10 .
b110 *
1$
#15000
0$
#15500
b10 0
1/
b100 .
b110 '
b110 -
b110 #
b110 ,
1$
#16000
0$
#16500
b100 0
0/
b10 .
b111 *
1$
#17000
0$
#17500
b10 0
1/
b100 .
b111 '
b111 -
b111 #
b111 ,
1$
#18000
0$
#18500
b100 0
0/
b10 .
b1000 *
1$
#19000
0$
#19500
b10 0
1/
b100 .
b1000 '
b1000 -
b1000 #
b1000 ,
1$
#20000
0$
#20500
b100 0
0/
b10 .
b1001 *
1$
#21000
0$
#21500
b10 0
1/
b100 .
b1001 '
b1001 -
b1001 #
b1001 ,
1$
#22000
0$
#22500
b100 0
0/
b10 .
b1010 *
1$
#23000
0$
#23500
b10 0
1/
b100 .
b1010 '
b1010 -
b1010 #
b1010 ,
1$
#24000
0$
#24500
b100 0
0/
b10 .
b1011 *
1$
#25000
0$
#25500
b10 0
1/
b100 .
b1011 '
b1011 -
b1011 #
b1011 ,
1$
#26000
0$
#26500
b100 0
0/
b10 .
b1100 *
1$
#27000
0$
#27500
b10 0
1/
b100 .
b1100 '
b1100 -
b1100 #
b1100 ,
1$
#28000
0$
#28500
b100 0
0/
b10 .
b1101 *
1$
#29000
0$
#29500
b10 0
1/
b100 .
b1101 '
b1101 -
b1101 #
b1101 ,
1$
#30000
0$
#30500
b100 0
0/
b10 .
b1110 *
1$
#31000
0$
#31500
b10 0
1/
b100 .
b1110 '
b1110 -
b1110 #
b1110 ,
1$
#32000
0$
#32500
b100 0
0/
b10 .
b1111 *
1$
#33000
0$
#33500
b10 0
1/
b100 .
b1111 '
b1111 -
b1111 #
b1111 ,
1$
#34000
0$
#34500
b100 0
0/
b10 .
b10000 *
1$
#35000
0$
#35500
b10 0
1/
b100 .
b10000 '
b10000 -
b10000 #
b10000 ,
1$
#36000
0$
#36500
b100 0
0/
b10 .
b10001 *
1$
#37000
0$
#37500
b10 0
1/
b100 .
b10001 '
b10001 -
b10001 #
b10001 ,
1$
#38000
0$
#38500
b100 0
0/
b10 .
b10010 *
1$
#39000
0$
#39500
b10 0
1/
b100 .
b10010 '
b10010 -
b10010 #
b10010 ,
1$
#40000
0$
#40500
b100 0
0/
b10 .
b10011 *
1$
#41000
0$
#41500
b10 0
1/
b100 .
b10011 '
b10011 -
b10011 #
b10011 ,
1$
#42000
0$
#42500
b100 0
0/
b10 .
b10100 *
1$
#43000
0$
#43500
b10 0
1/
b100 .
b10100 '
b10100 -
b10100 #
b10100 ,
1$
#44000
0$
#44500
b100 0
0/
b10 .
b10101 *
1$
#45000
0$
#45500
b10 0
1/
b100 .
b10101 '
b10101 -
b10101 #
b10101 ,
1$
#46000
0$
#46500
b100 0
0/
b10 .
b10110 *
1$
#47000
0$
#47500
b10 0
1/
b100 .
b10110 '
b10110 -
b10110 #
b10110 ,
1$
#48000
0$
#48500
b100 0
0/
b10 .
b10111 *
1$
#49000
0$
#49500
b10 0
1/
b100 .
b10111 '
b10111 -
b10111 #
b10111 ,
1$
#50000
0$
#50500
b100 0
0/
b10 .
b11000 *
1$
#51000
0$
#51500
b10 0
1/
b100 .
b11000 '
b11000 -
b11000 #
b11000 ,
1$
#52000
0$
#52500
b100 0
0/
b10 .
b11001 *
1$
#53000
0$
#53500
b10 0
1/
b100 .
b11001 '
b11001 -
b11001 #
b11001 ,
1$
#54000
0$
#54500
b100 0
0/
b10 .
b11010 *
1$
#55000
0$
#55500
b10 0
1/
b100 .
b11010 '
b11010 -
b11010 #
b11010 ,
1$
#56000
0$
#56500
b100 0
0/
b10 .
b11011 *
1$
#57000
0$
#57500
b10 0
1/
b100 .
b11011 '
b11011 -
b11011 #
b11011 ,
1$
#58000
0$
#58500
b100 0
0/
b10 .
b11100 *
1$
#59000
0$
#59500
b10 0
1/
b100 .
b11100 '
b11100 -
b11100 #
b11100 ,
1$
#60000
0$
#60500
b100 0
0/
b10 .
b11101 *
1$
#61000
0$
#61500
b10 0
1/
b100 .
b11101 '
b11101 -
b11101 #
b11101 ,
1$
#62000
0$
#62500
b100 0
0/
b10 .
b11110 *
1$
#63000
0$
#63500
b10 0
1/
b100 .
b11110 '
b11110 -
b11110 #
b11110 ,
1$
#64000
0$
#64500
b100 0
0/
b10 .
b11111 *
1$
#65000
0$
#65500
b10 0
1/
b100 .
b11111 '
b11111 -
b11111 #
b11111 ,
1$
#66000
0$
#66500
b100 0
0/
b10 .
b100000 *
1$
#67000
0$
#67500
b10 0
1/
b100 .
b100000 '
b100000 -
b100000 #
b100000 ,
1$
#68000
0$
#68500
b100 0
0/
b10 .
b100001 *
1$
#69000
0$
#69500
b10 0
1/
b100 .
b100001 '
b100001 -
b100001 #
b100001 ,
1$
#70000
0$
#70500
b100 0
0/
b10 .
b100010 *
1$
#71000
0$
#71500
b10 0
1/
b100 .
b100010 '
b100010 -
b100010 #
b100010 ,
1$
#72000
0$
#72500
b100 0
0/
b10 .
b100011 *
1$
#73000
0$
#73500
b10 0
1/
b100 .
b100011 '
b100011 -
b100011 #
b100011 ,
1$
#74000
0$
#74500
b100 0
0/
b10 .
b100100 *
1$
#75000
0$
#75500
b10 0
1/
b100 .
b100100 '
b100100 -
b100100 #
b100100 ,
1$
#76000
0$
#76500
b100 0
0/
b10 .
b100101 *
1$
#77000
0$
#77500
b10 0
1/
b100 .
b100101 '
b100101 -
b100101 #
b100101 ,
1$
#78000
0$
#78500
b100 0
0/
b10 .
b100110 *
1$
#79000
0$
#79500
b10 0
1/
b100 .
b100110 '
b100110 -
b100110 #
b100110 ,
1$
#80000
0$
#80500
b100 0
0/
b10 .
b100111 *
1$
#81000
0$
#81500
b10 0
1/
b100 .
b100111 '
b100111 -
b100111 #
b100111 ,
1$
#82000
0$
#82500
b100 0
0/
b10 .
b101000 *
1$
#83000
0$
#83500
b10 0
1/
b100 .
b101000 '
b101000 -
b101000 #
b101000 ,
1$
#84000
0$
#84500
b100 0
0/
b10 .
b101001 *
1$
#85000
0$
#85500
b10 0
1/
b100 .
b101001 '
b101001 -
b101001 #
b101001 ,
1$
#86000
0$
#86500
b100 0
0/
b10 .
b101010 *
1$
#87000
0$
#87500
b10 0
1/
b100 .
b101010 '
b101010 -
b101010 #
b101010 ,
1$
#88000
0$
#88500
b100 0
0/
b10 .
b101011 *
1$
#89000
0$
#89500
b10 0
1/
b100 .
b101011 '
b101011 -
b101011 #
b101011 ,
1$
#90000
0$
#90500
b100 0
0/
b10 .
b101100 *
1$
#91000
0$
#91500
b10 0
1/
b100 .
b101100 '
b101100 -
b101100 #
b101100 ,
1$
#92000
0$
#92500
b100 0
0/
b10 .
b101101 *
1$
#93000
0$
#93500
b10 0
1/
b100 .
b101101 '
b101101 -
b101101 #
b101101 ,
1$
#94000
0$
#94500
b100 0
0/
b10 .
b101110 *
1$
#95000
0$
#95500
b10 0
1/
b100 .
b101110 '
b101110 -
b101110 #
b101110 ,
1$
#96000
0$
#96500
b100 0
0/
b10 .
b101111 *
1$
#97000
0$
#97500
b10 0
1/
b100 .
b101111 '
b101111 -
b101111 #
b101111 ,
1$
#98000
0$
#98500
b100 0
0/
b10 .
b110000 *
1$
#99000
0$
#99500
b10 0
1/
b100 .
b110000 '
b110000 -
b110000 #
b110000 ,
1$
#100000
0$
#100500
b100 0
0/
b10 .
b110001 *
1$
#101000
0$
#101500
b10 0
1/
b100 .
b110001 '
b110001 -
b110001 #
b110001 ,
1$
#102000
0$
#102500
b100 0
0/
b10 .
b110010 *
1$
#103000
0$
#103500
b10 0
1/
b100 .
b110010 '
b110010 -
b110010 #
b110010 ,
1$
#104000
0$
#104500
b100 0
0/
b10 .
b110011 *
1$
#105000
0$
#105500
b10 0
1/
b100 .
b110011 '
b110011 -
b110011 #
b110011 ,
1$
#106000
0$
#106500
b100 0
0/
b10 .
b110100 *
1$
#107000
0$
#107500
b10 0
1/
b100 .
b110100 '
b110100 -
b110100 #
b110100 ,
1$
#108000
0$
#108500
b100 0
0/
b10 .
b110101 *
1$
#109000
0$
#109500
b10 0
1/
b100 .
b110101 '
b110101 -
b110101 #
b110101 ,
1$
#110000
0$
#110500
b100 0
0/
b10 .
b110110 *
1$
#111000
0$
#111500
b10 0
1/
b100 .
b110110 '
b110110 -
b110110 #
b110110 ,
1$
#112000
0$
#112500
b100 0
0/
b10 .
b110111 *
1$
#113000
0$
#113500
b10 0
1/
b100 .
b110111 '
b110111 -
b110111 #
b110111 ,
1$
#114000
0$
#114500
b100 0
0/
b10 .
b111000 *
1$
#115000
0$
#115500
b10 0
1/
b100 .
b111000 '
b111000 -
b111000 #
b111000 ,
1$
#116000
0$
#116500
b100 0
0/
b10 .
b111001 *
1$
#117000
0$
#117500
b10 0
1/
b100 .
b111001 '
b111001 -
b111001 #
b111001 ,
1$
#118000
0$
#118500
b100 0
0/
b10 .
b111010 *
1$
#119000
0$
#119500
b10 0
1/
b100 .
b111010 '
b111010 -
b111010 #
b111010 ,
1$
#120000
0$
#120500
b100 0
0/
b10 .
b111011 *
1$
#121000
0$
#121500
b10 0
1/
b100 .
b111011 '
b111011 -
b111011 #
b111011 ,
1$
#122000
0$
#122500
b100 0
0/
b10 .
b111100 *
1$
#123000
0$
#123500
b10 0
1/
b100 .
b111100 '
b111100 -
b111100 #
b111100 ,
1$
#124000
0$
#124500
b100 0
0/
b10 .
b111101 *
1$
#125000
0$
#125500
b10 0
1/
b100 .
b111101 '
b111101 -
b111101 #
b111101 ,
1$
#126000
0$
#126500
b100 0
0/
b10 .
b111110 *
1$
#127000
0$
#127500
b10 0
1/
b100 .
b111110 '
b111110 -
b111110 #
b111110 ,
1$
#128000
0$
#128500
b100 0
0/
b10 .
b111111 *
1$
#129000
0$
#129500
b10 0
1/
b100 .
b111111 '
b111111 -
b111111 #
b111111 ,
1$
#130000
0$
#130500
b100 0
0/
b10 .
b1000000 *
1$
#131000
0$
#131500
b10 0
1/
b100 .
b1000000 '
b1000000 -
b1000000 #
b1000000 ,
1$
#132000
0$
#132500
b100 0
0/
b10 .
b1000001 *
1$
#133000
0$
#133500
b10 0
1/
b100 .
b1000001 '
b1000001 -
b1000001 #
b1000001 ,
1$
#134000
0$
#134500
b100 0
0/
b10 .
b1000010 *
1$
#135000
0$
#135500
b10 0
1/
b100 .
b1000010 '
b1000010 -
b1000010 #
b1000010 ,
1$
#136000
0$
#136500
b100 0
0/
b10 .
b1000011 *
1$
#137000
0$
#137500
b10 0
1/
b100 .
b1000011 '
b1000011 -
b1000011 #
b1000011 ,
1$
#138000
0$
#138500
b100 0
0/
b10 .
b1000100 *
1$
#139000
0$
#139500
b10 0
1/
b100 .
b1000100 '
b1000100 -
b1000100 #
b1000100 ,
1$
#140000
0$
#140500
b100 0
0/
b10 .
b1000101 *
1$
#141000
0$
#141500
b10 0
1/
b100 .
b1000101 '
b1000101 -
b1000101 #
b1000101 ,
1$
#142000
0$
#142500
b100 0
0/
b10 .
b1000110 *
1$
#143000
0$
#143500
b10 0
1/
b100 .
b1000110 '
b1000110 -
b1000110 #
b1000110 ,
1$
#144000
0$
#144500
b100 0
0/
b10 .
b1000111 *
1$
#145000
0$
#145500
b10 0
1/
b100 .
b1000111 '
b1000111 -
b1000111 #
b1000111 ,
1$
#146000
0$
#146500
b100 0
0/
b10 .
b1001000 *
1$
#147000
0$
#147500
b10 0
1/
b100 .
b1001000 '
b1001000 -
b1001000 #
b1001000 ,
1$
#148000
0$
#148500
b100 0
0/
b10 .
b1001001 *
1$
#149000
0$
#149500
b10 0
1/
b100 .
b1001001 '
b1001001 -
b1001001 #
b1001001 ,
1$
#150000
0$
#150500
b100 0
0/
b10 .
b1001010 *
1$
#151000
0$
#151500
b10 0
1/
b100 .
b1001010 '
b1001010 -
b1001010 #
b1001010 ,
1$
#152000
0$
#152500
b100 0
0/
b10 .
b1001011 *
1$
#153000
0$
#153500
b10 0
1/
b100 .
b1001011 '
b1001011 -
b1001011 #
b1001011 ,
1$
#154000
0$
#154500
b100 0
0/
b10 .
b1001100 *
1$
#155000
0$
#155500
b10 0
1/
b100 .
b1001100 '
b1001100 -
b1001100 #
b1001100 ,
1$
#156000
0$
#156500
b100 0
0/
b10 .
b1001101 *
1$
#157000
0$
#157500
b10 0
1/
b100 .
b1001101 '
b1001101 -
b1001101 #
b1001101 ,
1$
#158000
0$
#158500
b100 0
0/
b10 .
b1001110 *
1$
#159000
0$
#159500
b10 0
1/
b100 .
b1001110 '
b1001110 -
b1001110 #
b1001110 ,
1$
#160000
0$
#160500
b100 0
0/
b10 .
b1001111 *
1$
#161000
0$
#161500
b10 0
1/
b100 .
b1001111 '
b1001111 -
b1001111 #
b1001111 ,
1$
#162000
0$
#162500
b100 0
0/
b10 .
b1010000 *
1$
#163000
0$
#163500
b10 0
1/
b100 .
b1010000 '
b1010000 -
b1010000 #
b1010000 ,
1$
#164000
0$
#164500
b100 0
0/
b10 .
b1010001 *
1$
#165000
0$
#165500
b10 0
1/
b100 .
b1010001 '
b1010001 -
b1010001 #
b1010001 ,
1$
#166000
0$
#166500
b100 0
0/
b10 .
b1010010 *
1$
#167000
0$
#167500
b10 0
1/
b100 .
b1010010 '
b1010010 -
b1010010 #
b1010010 ,
1$
#168000
0$
#168500
b100 0
0/
b10 .
b1010011 *
1$
#169000
0$
#169500
b10 0
1/
b100 .
b1010011 '
b1010011 -
b1010011 #
b1010011 ,
1$
#170000
0$
#170500
b100 0
0/
b10 .
b1010100 *
1$
#171000
0$
#171500
b10 0
1/
b100 .
b1010100 '
b1010100 -
b1010100 #
b1010100 ,
1$
#172000
0$
#172500
b100 0
0/
b10 .
b1010101 *
1$
#173000
0$
#173500
b10 0
1/
b100 .
b1010101 '
b1010101 -
b1010101 #
b1010101 ,
1$
#174000
0$
#174500
b100 0
0/
b10 .
b1010110 *
1$
#175000
0$
#175500
b10 0
1/
b100 .
b1010110 '
b1010110 -
b1010110 #
b1010110 ,
1$
#176000
0$
#176500
b100 0
0/
b10 .
b1010111 *
1$
#177000
0$
#177500
b10 0
1/
b100 .
b1010111 '
b1010111 -
b1010111 #
b1010111 ,
1$
#178000
0$
#178500
b100 0
0/
b10 .
b1011000 *
1$
#179000
0$
#179500
b10 0
1/
b100 .
b1011000 '
b1011000 -
b1011000 #
b1011000 ,
1$
#180000
0$
#180500
b100 0
0/
b10 .
b1011001 *
1$
#181000
0$
#181500
b10 0
1/
b100 .
b1011001 '
b1011001 -
b1011001 #
b1011001 ,
1$
#182000
0$
#182500
b100 0
0/
b10 .
b1011010 *
1$
#183000
0$
#183500
b10 0
1/
b100 .
b1011010 '
b1011010 -
b1011010 #
b1011010 ,
1$
#184000
0$
#184500
b100 0
0/
b10 .
b1011011 *
1$
#185000
0$
#185500
b10 0
1/
b100 .
b1011011 '
b1011011 -
b1011011 #
b1011011 ,
1$
#186000
0$
#186500
b100 0
0/
b10 .
b1011100 *
1$
#187000
0$
#187500
b10 0
1/
b100 .
b1011100 '
b1011100 -
b1011100 #
b1011100 ,
1$
#188000
0$
#188500
b100 0
0/
b10 .
b1011101 *
1$
#189000
0$
#189500
b10 0
1/
b100 .
b1011101 '
b1011101 -
b1011101 #
b1011101 ,
1$
#190000
0$
#190500
b100 0
0/
b10 .
b1011110 *
1$
#191000
0$
#191500
b10 0
1/
b100 .
b1011110 '
b1011110 -
b1011110 #
b1011110 ,
1$
#192000
0$
#192500
b100 0
0/
b10 .
b1011111 *
1$
#193000
0$
#193500
b10 0
1/
b100 .
b1011111 '
b1011111 -
b1011111 #
b1011111 ,
1$
#194000
0$
#194500
b100 0
0/
b10 .
b1100000 *
1$
#195000
0$
#195500
b10 0
1/
b100 .
b1100000 '
b1100000 -
b1100000 #
b1100000 ,
1$
#196000
0$
#196500
b100 0
0/
b10 .
b1100001 *
1$
#197000
0$
#197500
b10 0
1/
b100 .
b1100001 '
b1100001 -
b1100001 #
b1100001 ,
1$
#198000
0$
#198500
b100 0
0/
b10 .
b1100010 *
1$
#199000
0$
#199500
b10 0
1/
b100 .
b1100010 '
b1100010 -
b1100010 #
b1100010 ,
1$
#200000
0$
#200500
b100 0
0/
b10 .
b1100011 *
1$
#201000
0$
#201500
b10 0
1/
b100 .
b1100011 '
b1100011 -
b1100011 #
b1100011 ,
1$
#202000
0$
#202500
b100 0
0/
b10 .
b1100100 *
1$
#203000
0$
#203500
b10 0
1/
b100 .
b1100100 '
b1100100 -
b1100100 #
b1100100 ,
1$
#204000
0$
#204500
b100 0
0/
b10 .
b1100101 *
1$
#205000
0$
#205500
b10 0
1/
b100 .
b1100101 '
b1100101 -
b1100101 #
b1100101 ,
1$
#206000
0$
#206500
b100 0
0/
b10 .
b1100110 *
1$
#207000
0$
#207500
b10 0
1/
b100 .
b1100110 '
b1100110 -
b1100110 #
b1100110 ,
1$
#208000
0$
#208500
b100 0
0/
b10 .
b1100111 *
1$
#209000
0$
#209500
b10 0
1/
b100 .
b1100111 '
b1100111 -
b1100111 #
b1100111 ,
1$
#210000
0$
#210500
b100 0
0/
b10 .
b1101000 *
1$
#211000
0$
#211500
b10 0
1/
b100 .
b1101000 '
b1101000 -
b1101000 #
b1101000 ,
1$
#212000
0$
#212500
b100 0
0/
b10 .
b1101001 *
1$
#213000
0$
#213500
b10 0
1/
b100 .
b1101001 '
b1101001 -
b1101001 #
b1101001 ,
1$
#214000
0$
#214500
b100 0
0/
b10 .
b1101010 *
1$
#215000
0$
#215500
b10 0
1/
b100 .
b1101010 '
b1101010 -
b1101010 #
b1101010 ,
1$
#216000
0$
#216500
b100 0
0/
b10 .
b1101011 *
1$
#217000
0$
#217500
b10 0
1/
b100 .
b1101011 '
b1101011 -
b1101011 #
b1101011 ,
1$
#218000
0$
#218500
b100 0
0/
b10 .
b1101100 *
1$
#219000
0$
#219500
b10 0
1/
b100 .
b1101100 '
b1101100 -
b1101100 #
b1101100 ,
1$
#220000
0$
#220500
b100 0
0/
b10 .
b1101101 *
1$
#221000
0$
#221500
b10 0
1/
b100 .
b1101101 '
b1101101 -
b1101101 #
b1101101 ,
1$
#222000
0$
#222500
b100 0
0/
b10 .
b1101110 *
1$
#223000
0$
#223500
b10 0
1/
b100 .
b1101110 '
b1101110 -
b1101110 #
b1101110 ,
1$
#224000
0$
#224500
b100 0
0/
b10 .
b1101111 *
1$
#225000
0$
#225500
b10 0
1/
b100 .
b1101111 '
b1101111 -
b1101111 #
b1101111 ,
1$
#226000
0$
#226500
b100 0
0/
b10 .
b1110000 *
1$
#227000
0$
#227500
b10 0
1/
b100 .
b1110000 '
b1110000 -
b1110000 #
b1110000 ,
1$
#228000
0$
#228500
b100 0
0/
b10 .
b1110001 *
1$
#229000
0$
#229500
b10 0
1/
b100 .
b1110001 '
b1110001 -
b1110001 #
b1110001 ,
1$
#230000
0$
#230500
b100 0
0/
b10 .
b1110010 *
1$
#231000
0$
#231500
b10 0
1/
b100 .
b1110010 '
b1110010 -
b1110010 #
b1110010 ,
1$
#232000
0$
#232500
b100 0
0/
b10 .
b1110011 *
1$
#233000
0$
#233500
b10 0
1/
b100 .
b1110011 '
b1110011 -
b1110011 #
b1110011 ,
1$
#234000
0$
#234500
b100 0
0/
b10 .
b1110100 *
1$
#235000
0$
#235500
b10 0
1/
b100 .
b1110100 '
b1110100 -
b1110100 #
b1110100 ,
1$
#236000
0$
#236500
b100 0
0/
b10 .
b1110101 *
1$
#237000
0$
#237500
b10 0
1/
b100 .
b1110101 '
b1110101 -
b1110101 #
b1110101 ,
1$
#238000
0$
#238500
b100 0
0/
b10 .
b1110110 *
1$
#239000
0$
#239500
b10 0
1/
b100 .
b1110110 '
b1110110 -
b1110110 #
b1110110 ,
1$
#240000
0$
#240500
b100 0
0/
b10 .
b1110111 *
1$
#241000
0$
#241500
b10 0
1/
b100 .
b1110111 '
b1110111 -
b1110111 #
b1110111 ,
1$
#242000
0$
#242500
b100 0
0/
b10 .
b1111000 *
1$
#243000
0$
#243500
b10 0
1/
b100 .
b1111000 '
b1111000 -
b1111000 #
b1111000 ,
1$
#244000
0$
#244500
b100 0
0/
b10 .
b1111001 *
1$
#245000
0$
#245500
b10 0
1/
b100 .
b1111001 '
b1111001 -
b1111001 #
b1111001 ,
1$
#246000
0$
#246500
b100 0
0/
b10 .
b1111010 *
1$
#247000
0$
#247500
b10 0
1/
b100 .
b1111010 '
b1111010 -
b1111010 #
b1111010 ,
1$
#248000
0$
#248500
b100 0
0/
b10 .
b1111011 *
1$
#249000
0$
#249500
b10 0
1/
b100 .
b1111011 '
b1111011 -
b1111011 #
b1111011 ,
1$
#250000
0$
#250500
b100 0
0/
b10 .
b1111100 *
1$
#251000
0$
#251500
b10 0
1/
b100 .
b1111100 '
b1111100 -
b1111100 #
b1111100 ,
1$
#252000
0$
#252500
b100 0
0/
b10 .
b1111101 *
1$
#253000
0$
#253500
b10 0
1/
b100 .
b1111101 '
b1111101 -
b1111101 #
b1111101 ,
1$
#254000
0$
#254500
b100 0
0/
b10 .
b1111110 *
1$
#255000
0$
#255500
b10 0
1/
b100 .
b1111110 '
b1111110 -
b1111110 #
b1111110 ,
1$
#256000
0$
#256500
b100 0
0/
b10 .
b1111111 *
1$
#257000
0$
#257500
b10 0
1/
b100 .
b1111111 '
b1111111 -
b1111111 #
b1111111 ,
1$
#258000
0$
#258500
b100 0
0/
b10 .
b10000000 *
1$
#259000
0$
#259500
b10 0
1/
b100 .
b10000000 '
b10000000 -
b10000000 #
b10000000 ,
1$
#260000
0$
#260500
b100 0
0/
b10 .
b10000001 *
1$
#261000
0$
#261500
b10 0
1/
b100 .
b10000001 '
b10000001 -
b10000001 #
b10000001 ,
1$
#262000
0$
#262500
b100 0
0/
b10 .
b10000010 *
1$
#263000
0$
#263500
b10 0
1/
b100 .
b10000010 '
b10000010 -
b10000010 #
b10000010 ,
1$
#264000
0$
#264500
b100 0
0/
b10 .
b10000011 *
1$
#265000
0$
#265500
b10 0
1/
b100 .
b10000011 '
b10000011 -
b10000011 #
b10000011 ,
1$
#266000
0$
#266500
b100 0
0/
b10 .
b10000100 *
1$
#267000
0$
#267500
b10 0
1/
b100 .
b10000100 '
b10000100 -
b10000100 #
b10000100 ,
1$
#268000
0$
#268500
b100 0
0/
b10 .
b10000101 *
1$
#269000
0$
#269500
b10 0
1/
b100 .
b10000101 '
b10000101 -
b10000101 #
b10000101 ,
1$
#270000
0$
#270500
b100 0
0/
b10 .
b10000110 *
1$
#271000
0$
#271500
b10 0
1/
b100 .
b10000110 '
b10000110 -
b10000110 #
b10000110 ,
1$
#272000
0$
#272500
b100 0
0/
b10 .
b10000111 *
1$
#273000
0$
#273500
b10 0
1/
b100 .
b10000111 '
b10000111 -
b10000111 #
b10000111 ,
1$
#274000
0$
#274500
b100 0
0/
b10 .
b10001000 *
1$
#275000
0$
#275500
b10 0
1/
b100 .
b10001000 '
b10001000 -
b10001000 #
b10001000 ,
1$
#276000
0$
